<?xml version="1.0" encoding="UTF-8"?>
<QCARConfig xmlns:xsi="http://www.w3.org/2001/XMLSchema-instance" xsi:noNamespaceSchemaLocation="qcar_config.xsd">
  <Tracking>
    <ImageTarget name="118_Oganeson" size="1.000000 1.333333" />
    <ImageTarget name="117_Teneso" size="1.000000 1.333333" />
    <ImageTarget name="116_Livermorio" size="1.000000 1.333333" />
    <ImageTarget name="115_Moscovio" size="1.000000 1.333333" />
    <ImageTarget name="114_Flerovio" size="1.000000 1.333333" />
    <ImageTarget name="113_Nihonio" size="1.000000 1.333333" />
    <ImageTarget name="112_Copernicio" size="1.000000 1.333333" />
    <ImageTarget name="111_Roentgenio" size="1.000000 1.333333" />
    <ImageTarget name="110_Darmstatio" size="1.000000 1.333333" />
    <ImageTarget name="109_Meitnerio" size="1.000000 1.333333" />
    <ImageTarget name="108_Hassio" size="1.000000 1.333333" />
    <ImageTarget name="107_Bohrio" size="1.000000 1.333333" />
    <ImageTarget name="106_Seaborgio" size="1.000000 1.333333" />
    <ImageTarget name="105_Dubnio" size="1.000000 1.333333" />
    <ImageTarget name="104_Rutherfordio" size="1.000000 1.333333" />
    <ImageTarget name="103_Laurencio" size="1.000000 1.333333" />
    <ImageTarget name="102_Nobelio" size="1.000000 1.333333" />
    <ImageTarget name="101_Mendelevio" size="1.000000 1.333333" />
    <ImageTarget name="100_Fermio" size="1.000000 1.333333" />
    <ImageTarget name="99_Einstenio" size="1.000000 1.333333" />
    <ImageTarget name="98_Californio" size="1.000000 1.333333" />
    <ImageTarget name="97_Berkelio" size="1.000000 1.333333" />
    <ImageTarget name="96_Curio" size="1.000000 1.333333" />
    <ImageTarget name="95_Americio" size="1.000000 1.333333" />
    <ImageTarget name="94_Plutonio" size="1.000000 1.333333" />
    <ImageTarget name="93_Neptunio" size="1.000000 1.333333" />
    <ImageTarget name="92_Uranio" size="1.000000 1.333333" />
    <ImageTarget name="91_Protactinio" size="1.000000 1.333333" />
    <ImageTarget name="90_Torio" size="1.000000 1.333333" />
    <ImageTarget name="89_Actinio" size="1.000000 1.333333" />
    <ImageTarget name="88_Radio" size="1.000000 1.333333" />
    <ImageTarget name="87_Francio" size="1.000000 1.333333" />
    <ImageTarget name="86_Radon" size="1.000000 1.333333" />
    <ImageTarget name="85_Astato" size="1.000000 1.333333" />
    <ImageTarget name="84_Polonio" size="1.000000 1.333333" />
    <ImageTarget name="83_Bismuto" size="1.000000 1.333333" />
    <ImageTarget name="82_Plomo" size="1.000000 1.333333" />
    <ImageTarget name="81_Talio" size="1.000000 1.333333" />
    <ImageTarget name="80_Mercurio" size="1.000000 1.333333" />
    <ImageTarget name="79_Oro" size="1.000000 1.333333" />
    <ImageTarget name="78_Platino" size="1.000000 1.333333" />
    <ImageTarget name="77_Iridio" size="1.000000 1.333333" />
    <ImageTarget name="76_Osmio" size="1.000000 1.333333" />
    <ImageTarget name="75_Renio" size="1.000000 1.333333" />
    <ImageTarget name="74_Wolframio" size="1.000000 1.333333" />
    <ImageTarget name="73_Tantalio" size="1.000000 1.333333" />
    <ImageTarget name="72_Hafnio" size="1.000000 1.333333" />
    <ImageTarget name="71_Lutecio" size="1.000000 1.333333" />
    <ImageTarget name="70_Iterbio" size="1.000000 1.333333" />
    <ImageTarget name="69_Tulio" size="1.000000 1.333333" />
    <ImageTarget name="68_Erbio" size="1.000000 1.333333" />
    <ImageTarget name="67_Holmio" size="1.000000 1.333333" />
    <ImageTarget name="66_Disprosio" size="1.000000 1.333333" />
    <ImageTarget name="65_Terbio" size="1.000000 1.333333" />
    <ImageTarget name="64_Gadolinio" size="1.000000 1.333333" />
    <ImageTarget name="63_Europio" size="1.000000 1.333333" />
    <ImageTarget name="62_Samario" size="1.000000 1.333333" />
    <ImageTarget name="61_Prometio" size="1.000000 1.333333" />
    <ImageTarget name="60_Neodimio" size="1.000000 1.333333" />
    <ImageTarget name="59_Praseodimio" size="1.000000 1.333333" />
    <ImageTarget name="58_Cerio" size="1.000000 1.333333" />
    <ImageTarget name="57_Lantano" size="1.000000 1.333333" />
    <ImageTarget name="56_Bario" size="1.000000 1.333333" />
    <ImageTarget name="55_Cesio" size="1.000000 1.333333" />
    <ImageTarget name="54_Xenon" size="1.000000 1.333333" />
    <ImageTarget name="53_Yodo" size="1.000000 1.333333" />
    <ImageTarget name="52_Telurio" size="1.000000 1.333333" />
    <ImageTarget name="51_Antimonio" size="1.000000 1.333333" />
    <ImageTarget name="50_Estano" size="1.000000 1.333333" />
    <ImageTarget name="49_Indio" size="1.000000 1.333333" />
    <ImageTarget name="48_Cadmio" size="1.000000 1.333333" />
    <ImageTarget name="47_Plata" size="1.000000 1.333333" />
    <ImageTarget name="46_Paladio" size="1.000000 1.333333" />
    <ImageTarget name="45_Rodio" size="1.000000 1.333333" />
    <ImageTarget name="44_Rutenio" size="1.000000 1.333333" />
    <ImageTarget name="43_Tecnecio" size="1.000000 1.333333" />
    <ImageTarget name="42_Molibdeno" size="1.000000 1.333333" />
    <ImageTarget name="41_Niobio" size="1.000000 1.333333" />
    <ImageTarget name="40_Zirconio" size="1.000000 1.333333" />
    <ImageTarget name="39_Itrio" size="1.000000 1.333333" />
    <ImageTarget name="38_Estroncio" size="1.000000 1.333333" />
    <ImageTarget name="37_Rubidio" size="1.000000 1.333333" />
    <ImageTarget name="36_Kripton" size="1.000000 1.333333" />
    <ImageTarget name="35_Bromo" size="1.000000 1.333333" />
    <ImageTarget name="34_Selenio" size="1.000000 1.333333" />
    <ImageTarget name="33_Arsenico" size="1.000000 1.333333" />
    <ImageTarget name="32_Germanio" size="1.000000 1.333333" />
    <ImageTarget name="31_Galio" size="1.000000 1.333333" />
    <ImageTarget name="30_Zinc" size="1.000000 1.333333" />
    <ImageTarget name="29_Cobre" size="1.000000 1.333333" />
    <ImageTarget name="28_Niquel" size="1.000000 1.333333" />
    <ImageTarget name="27_Cobalto" size="1.000000 1.333333" />
    <ImageTarget name="26_Hierro" size="1.000000 1.333333" />
    <ImageTarget name="25_Manganeso" size="1.000000 1.333333" />
    <ImageTarget name="24_Cromo" size="1.000000 1.333333" />
    <ImageTarget name="23_Vanadio" size="1.000000 1.333333" />
    <ImageTarget name="22_Titanio" size="1.000000 1.333333" />
    <ImageTarget name="21_Escandio" size="1.000000 1.333333" />
    <ImageTarget name="20_Calcio" size="1.000000 1.333333" />
    <ImageTarget name="19_Potasio" size="1.000000 1.333333" />
    <ImageTarget name="18_Argon" size="1.000000 1.333333" />
    <ImageTarget name="17_Cloro" size="1.000000 1.333333" />
    <ImageTarget name="16_Azufre" size="1.000000 1.333333" />
    <ImageTarget name="15_Fosforo" size="1.000000 1.333333" />
    <ImageTarget name="14_Silicio" size="1.000000 1.333333" />
    <ImageTarget name="13_Aluminio" size="1.000000 1.333333" />
    <ImageTarget name="12_Magnesio" size="1.000000 1.333333" />
    <ImageTarget name="11_Sodio" size="1.000000 1.333333" />
    <ImageTarget name="10_Neon" size="1.000000 1.333333" />
    <ImageTarget name="09_Fluor" size="1.000000 1.333333" />
    <ImageTarget name="08_Oxigeno" size="1.000000 1.333333" />
    <ImageTarget name="07_Nitrogeno" size="1.000000 1.333333" />
    <ImageTarget name="06_Carbono" size="1.000000 1.333333" />
    <ImageTarget name="05_Boro" size="1.000000 1.333333" />
    <ImageTarget name="04_Berilio" size="1.000000 1.333333" />
    <ImageTarget name="03_Litio" size="1.000000 1.333333" />
    <ImageTarget name="02_Helio" size="1.000000 1.333333" />
    <ImageTarget name="01_Hidrogeno" size="1.000000 1.333333" />
  </Tracking>
</QCARConfig>
